LICENSE
MANIFEST.in
README.md
setup.py
reneo/__init__.py
reneo/__main__.py
reneo/reneo.CITATION
reneo/reneo.LICENSE
reneo/reneo.VERSION
reneo.egg-info/PKG-INFO
reneo.egg-info/SOURCES.txt
reneo.egg-info/dependency_links.txt
reneo.egg-info/entry_points.txt
reneo.egg-info/requires.txt
reneo.egg-info/top_level.txt
reneo/config/config.yaml
reneo/config/databases.yaml
reneo/test_data/AllVOG.hmm
reneo/test_data/assemblyGraph.gfa
reneo/test_data/marker.hmm
reneo/test_data/reads/A13-04-182-06_TAGCTT_R1.fastq.gz
reneo/test_data/reads/A13-04-182-06_TAGCTT_R2.fastq.gz
reneo/test_data/reads/A13-12-250-06_GGCTAC_R1.fastq.gz
reneo/test_data/reads/A13-12-250-06_GGCTAC_R2.fastq.gz
reneo/workflow/install.smk
reneo/workflow/reneo.smk
reneo/workflow/envs/curl.yaml
reneo/workflow/envs/genes.yaml
reneo/workflow/envs/koverage.yaml
reneo/workflow/envs/mapping.yaml
reneo/workflow/envs/reneo.yaml
reneo/workflow/rules/coverage.smk
reneo/workflow/rules/databases.smk
reneo/workflow/rules/genes.smk
reneo/workflow/rules/gfa2fasta.smk
reneo/workflow/rules/postprocess.smk
reneo/workflow/rules/preflight.smk
reneo/workflow/rules/reneo.smk
reneo/workflow/rules/targets.smk
reneo/workflow/scripts/combineJunctionPickles.py
reneo/workflow/scripts/format_koverage_results.py
reneo/workflow/scripts/gfa2fasta.py
reneo/workflow/scripts/reneo.py
reneo/workflow/scripts/sampleJunctions.py
reneo/workflow/scripts/reneo_utils/FD_Inexact.py
reneo/workflow/scripts/reneo_utils/__init__.py
reneo/workflow/scripts/reneo_utils/component_utils.py
reneo/workflow/scripts/reneo_utils/coverage_utils.py
reneo/workflow/scripts/reneo_utils/edge_graph_utils.py
reneo/workflow/scripts/reneo_utils/flow_utils.py
reneo/workflow/scripts/reneo_utils/gene_utils.py
reneo/workflow/scripts/reneo_utils/genome_utils.py
reneo/workflow/scripts/reneo_utils/output_utils.py
tests/test_reneo.py