Metadata-Version: 2.1
Name: reneo
Version: 0.5.0
Summary: Unraveling Viral Genomes from Metagenomes
Home-page: https://github.com/Vini2/reneo
Author: Vijini Mallawaarachchi
Author-email: viji.mallawaarachchi@gmail.com
Classifier: Development Status :: 4 - Beta
Classifier: Programming Language :: Python :: 3
Classifier: License :: OSI Approved :: MIT License
Classifier: Natural Language :: English
Classifier: Topic :: Scientific/Engineering :: Bio-Informatics
Classifier: Operating System :: OS Independent
Requires-Python: >=3.9
License-File: LICENSE
Requires-Dist: snakemake>=7.14.0
Requires-Dist: pyyaml>=6.0
Requires-Dist: click>=8.1.3
Requires-Dist: metasnek>=0.0.5
Requires-Dist: snaketool-utils>=0.0.4
